tests/__init__.py
tests/test_errors.py
tests/test_tomlconf.py
tomlconf/__init__.py
tomlconf/appdir.py
tomlconf/container.py
tomlconf/core.py
tomlconf/errors.py
tomlconf-0.3.dist-info/METADATA
tomlconf-0.3.dist-info/RECORD
tomlconf-0.3.dist-info/WHEEL
tomlconf-0.3.dist-info/top_level.txt
